{
    "paths": {
        "/thought/": {
            "post": {
                "summary": "Create a new thought",
                "operationId": "createThought",
                "tags": [
                    "Thoughts"
                ],
                "requestBody": {
                    "description": "Thought object to be created",
                    "required": true,
                    "content": {
                        "application/json": {
                            "schema": {
                                "$ref": "#/components/schemas/Thought"
                            }
                        }
                    }
                },
                "responses": {
                    "201": {
                        "description": "Thought created successfully",
                        "content": {
                            "application/json": {
                                "schema": {
                                    "$ref": "#/components/schemas/Thought"
                                }
                            }
                        }
                    },
                    "400": {
                        "$ref": "#/components/responses/ValidationError"
                    },
                    "401": {
                        "$ref": "#/components/responses/UnauthorizedError"
                    },
                    "409": {
                        "$ref": "#/components/responses/ConflictError"
                    },
                    "429": {
                        "$ref": "#/components/responses/TooManyRequestsError"
                    },
                    "500": {
                        "$ref": "#/components/responses/InternalServerError"
                    }
                },
                "security": [
                    {
                        "bearerAuth": []
                    }
                ]
            },
            "get": {
                "summary": "Get all thoughts",
                "operationId": "getAllThoughts",
                "tags": [
                    "Thoughts"
                ],
                "parameters": [
                    {
                        "$ref": "#/components/parameters/Offset"
                    },
                    {
                        "$ref": "#/components/parameters/Limit"
                    },
                    {
                        "$ref": "#/components/parameters/Sort"
                    },
                    {
                        "description": "TODO: Define filter parameters for Thought"
                    }
                ],
                "responses": {
                    "200": {
                        "description": "List of thoughts",
                        "content": {
                            "application/json": {
                                "schema": {
                                    "type": "array",
                                    "items": {
                                        "$ref": "#/components/schemas/Thought"
                                    }
                                }
                            }
                        }
                    },
                    "401": {
                        "$ref": "#/components/responses/UnauthorizedError"
                    },
                    "429": {
                        "$ref": "#/components/responses/TooManyRequestsError"
                    },
                    "500": {
                        "$ref": "#/components/responses/InternalServerError"
                    }
                },
                "security": [
                    {
                        "bearerAuth": []
                    }
                ]
            }
        },
        "/thought/{thought_id}/": {
            "get": {
                "summary": "Get a thought by id",
                "operationId": "getThoughtById",
                "tags": [
                    "Thoughts"
                ],
                "parameters": [
                    {
                        "$ref": "#/components/parameters/MongoId"
                    }
                ],
                "responses": {
                    "200": {
                        "description": "Thought found",
                        "content": {
                            "application/json": {
                                "schema": {
                                    "$ref": "#/components/schemas/Thought"
                                }
                            }
                        }
                    },
                    "401": {
                        "$ref": "#/components/responses/UnauthorizedError"
                    },
                    "404": {
                        "$ref": "#/components/responses/NotFoundError"
                    },
                    "429": {
                        "$ref": "#/components/responses/TooManyRequestsError"
                    },
                    "500": {
                        "$ref": "#/components/responses/InternalServerError"
                    }
                },
                "security": [
                    {
                        "bearerAuth": []
                    }
                ]
            },
            "put": {
                "summary": "Update a thought by id",
                "operationId": "updateThought",
                "tags": [
                    "Thoughts"
                ],
                "parameters": [
                    {
                        "$ref": "#/components/parameters/MongoId"
                    }
                ],
                "requestBody": {
                    "description": "Thought object to be updated",
                    "required": true,
                    "content": {
                        "application/json": {
                            "schema": {
                                "$ref": "#/components/schemas/Thought"
                            }
                        }
                    }
                },
                "responses": {
                    "200": {
                        "description": "Thought updated successfully",
                        "content": {
                            "application/json": {
                                "schema": {
                                    "$ref": "#/components/schemas/Thought"
                                }
                            }
                        }
                    },
                    "400": {
                        "$ref": "#/components/responses/ValidationError"
                    },
                    "401": {
                        "$ref": "#/components/responses/UnauthorizedError"
                    },
                    "404": {
                        "$ref": "#/components/responses/NotFoundError"
                    },
                    "429": {
                        "$ref": "#/components/responses/TooManyRequestsError"
                    },
                    "500": {
                        "$ref": "#/components/responses/InternalServerError"
                    }
                },
                "security": [
                    {
                        "bearerAuth": []
                    }
                ]
            },
            "delete": {
                "summary": "Delete a thought by id",
                "operationId": "deleteThought",
                "tags": [
                    "Thoughts"
                ],
                "parameters": [
                    {
                        "$ref": "#/components/parameters/MongoId"
                    }
                ],
                "responses": {
                    "200": {
                        "description": "Thought deleted successfully",
                        "content": {
                            "application/json": {
                                "schema": {
                                    "$ref": "#/components/schemas/Thought"
                                }
                            }
                        }
                    },
                    "401": {
                        "$ref": "#/components/responses/UnauthorizedError"
                    },
                    "404": {
                        "$ref": "#/components/responses/NotFoundError"
                    },
                    "429": {
                        "$ref": "#/components/responses/TooManyRequestsError"
                    },
                    "500": {
                        "$ref": "#/components/responses/InternalServerError"
                    }
                },
                "security": [
                    {
                        "bearerAuth": []
                    }
                ]
            }
        }
    }
}